LICENSE.txt
README.md
setup.cfg
setup.py
keeper_secrets_manager_core/__init__.py
keeper_secrets_manager_core/configkeys.py
keeper_secrets_manager_core/core.py
keeper_secrets_manager_core/crypto.py
keeper_secrets_manager_core/exceptions.py
keeper_secrets_manager_core/helpers.py
keeper_secrets_manager_core/keeper_globals.py
keeper_secrets_manager_core/mock.py
keeper_secrets_manager_core/storage.py
keeper_secrets_manager_core/utils.py
keeper_secrets_manager_core.egg-info/PKG-INFO
keeper_secrets_manager_core.egg-info/SOURCES.txt
keeper_secrets_manager_core.egg-info/dependency_links.txt
keeper_secrets_manager_core.egg-info/not-zip-safe
keeper_secrets_manager_core.egg-info/requires.txt
keeper_secrets_manager_core.egg-info/top_level.txt
keeper_secrets_manager_core/dto/__init__.py
keeper_secrets_manager_core/dto/dtos.py
keeper_secrets_manager_core/dto/payload.py