Metadata-Version: 2.4
Name: keeper-secrets-manager-core
Version: 17.0.0
Summary: Keeper Secrets Manager for Python 3
Home-page: https://github.com/Keeper-Security/secrets-manager
Author: Keeper Security
Author-email: sm@keepersecurity.com
License: MIT
Project-URL: Bug Tracker, https://github.com/Keeper-Security/secrets-manager/issues
Project-URL: Documentation, https://github.com/Keeper-Security/secrets-manager
Project-URL: Source Code, https://github.com/Keeper-Security/secrets-manager
Keywords: Keeper Password Manager SDK
Classifier: Development Status :: 5 - Production/Stable
Classifier: Intended Audience :: Developers
Classifier: License :: OSI Approved :: MIT License
Classifier: Operating System :: OS Independent
Classifier: Programming Language :: Python
Classifier: Programming Language :: Python :: 3
Classifier: Programming Language :: Python :: 3.6
Classifier: Programming Language :: Python :: 3.7
Classifier: Programming Language :: Python :: 3.8
Classifier: Programming Language :: Python :: 3.9
Classifier: Programming Language :: Python :: 3.10
Classifier: Programming Language :: Python :: 3.11
Classifier: Programming Language :: Python :: 3.12
Classifier: Topic :: Security
Requires-Python: >=3.6
License-File: LICENSE.txt
Requires-Dist: requests
Requires-Dist: cryptography>=39.0.1
Requires-Dist: importlib_metadata
Dynamic: author
Dynamic: author-email
Dynamic: classifier
Dynamic: description
Dynamic: description-content-type
Dynamic: home-page
Dynamic: keywords
Dynamic: license
Dynamic: license-file
Dynamic: project-url
Dynamic: requires-dist
Dynamic: requires-python
Dynamic: summary
